tax_id_generator/__init__.py
tax_id_generator/tax_id_gen.py
Ukr_TAX_ID_Generator-1.0.0.dist-info/LICENSE
Ukr_TAX_ID_Generator-1.0.0.dist-info/METADATA
Ukr_TAX_ID_Generator-1.0.0.dist-info/WHEEL
Ukr_TAX_ID_Generator-1.0.0.dist-info/top_level.txt
Ukr_TAX_ID_Generator-1.0.0.dist-info/RECORD
