Metadata-Version: 2.1
Name: Ukr-TAX-ID-Generator
Version: 1.0.0
Summary: This package generates Ukraine TAX ID by user birthday
Home-page: https://github.com/lozik4/UkrTaxIdGenerator
Author: Serhii Lozytskyi
Classifier: Programming Language :: Python :: 3
Classifier: License :: OSI Approved :: MIT License
License-File: LICENSE
